Metadata-Version: 2.1
Name: odoo8-addon-account-invoice-picking-address
Version: 8.0.1.0.0.99.dev18
Summary: Add Picking Address on invoice template
Home-page: UNKNOWN
Author: Agile Business Group, Odoo Community Association (OCA)
Author-email: support@odoo-community.org
License: AGPL-3
Platform: UNKNOWN
Classifier: Programming Language :: Python
Classifier: Framework :: Odoo
Classifier: License :: OSI Approved :: GNU Affero General Public License v3
Requires-Python: ~=2.7
Requires-Dist: odoo8-addon-stock-picking-invoice-link
Requires-Dist: odoo (<9.0a,>=8.0a)
